Full Adder/full_adder.v
module full_adder(A,B,C,s,c);

input A,B,C;
output s,c;

assign s = A ^ B ^ C;
assign c = (A&B) | (B&C) | (C&A);

endmodule

Full_Adder/TestBenches/full_adder_tb.v
`timescale 1 ns/1 ns
`include "../full_adder.v"

module full_adder_tb;

reg A,B,C;
wire s,c;

full_adder uut(A,B,C,s,c);

initial begin
    
    $dumpfile("full_adder.vcd");
    $dumpvars(0, full_adder_tb);

    {A,B,C} = 3'b000;#20;
    {A,B,C} = 3'b100;#20;
    {A,B,C} = 3'b010;#20;
    {A,B,C} = 3'b001;#20;
    {A,B,C} = 3'b110;#20;
    {A,B,C} = 3'b101;#20;
    {A,B,C} = 3'b011;#20;
    {A,B,C} = 3'b111;#20;

    $display("Test Completed!");

end

endmodule

Full Adder/TestBenches/full_adder.vcd
$date
	Fri Aug 22 18:31:08 2025
$end
$version
	Icarus Verilog
$end
$timescale
	1ns
$end
$scope module full_adder_tb $end
$var wire 1 ! s $end
$var wire 1 " c $end
$var reg 1 # A $end
$var reg 1 $ B $end
$var reg 1 % C $end
$scope module uut $end
$var wire 1 # A $end
$var wire 1 $ B $end
$var wire 1 % C $end
$var wire 1 " c $end
$var wire 1 ! s $end
$upscope $end
$upscope $end
$enddefinitions $end
#0
$dumpvars
0%
0$
0#
0"
0!
$end
#20
1!
1#
#40
0#
1$
#60
1!
0$
1%
#80
1"
0!
1#
1$
0%
#100
0!
0$
1%
#120
0#
1$
#140
1!
1#
